{
  "birds": [
    {
      "id": 1,
      "name": "duck",
      "number": "3"
    },
    {
      "id": "NMY0Cj7ZNchf9IQgSKgVC",
      "name": "canada goose",
      "number": "18"
    },
    {
      "id": "yQk-RIM7yvBpm3xJArc-R",
      "name": "blue tit",
      "number": "1"
    },
    {
      "id": "c1ivP5IvKzds08LUJEK_1",
      "name": "falcon",
      "number": "1"
    },
    {
      "id": "243oIqfznyXIrH5i_C-ab",
      "name": "blue tit",
      "number": "1"
    },
    {
      "id": "hAepiHWTjlPxSvgFIY3tX",
      "name": "blue tit",
      "number": "1"
    },
    {
      "id": "vx_3Nnc3BTxwNjw6n8Iy8",
      "name": "blue tit",
      "number": "1"
    },
    {
      "id": "GFXvx48_MlDz6sWFQYevt",
      "name": "blue tit",
      "number": "1"
    },
    {
      "id": "MjVBQ6y_STFIdQHdwfOlZ",
      "name": "blue tit",
      "number": "1"
    },
    {
      "id": "qX1ZG4NIY93YidUowqz3_",
      "name": "blue tit",
      "number": "1"
    },
    {
      "id": "8Nw-4uI_n2XJH68PXvZPt",
      "name": "blue tit",
      "number": "1"
    },
    {
      "id": "Ue5grEKTPjLXHoayaeWbP",
      "name": "collar dove",
      "number": "2"
    },
    {
      "id": "yJZu5qNAEsWQjDuB83Z7K",
      "name": "",
      "number": ""
    },
    {
      "id": "eHWHUPncbT9LYawiULh0A",
      "name": "",
      "number": ""
    },
    {
      "id": "URYOq9Rj8JJ7RecMnLVle",
      "name": "",
      "number": ""
    },
    {
      "id": "Y6Cqu44vfwGqo_4PESL07",
      "name": "",
      "number": ""
    },
    {
      "id": "Uj_E5QR6gPDP-BIUW5C3q",
      "name": "",
      "number": ""
    },
    {
      "id": "mPRIhU_SCwbslkq7S_wSe",
      "name": "",
      "number": ""
    },
    {
      "id": "j5rWoIdi9bN3F-8p4pMNv",
      "name": "",
      "number": ""
    },
    {
      "id": "Wl3Z0nxQnWtFgHyIxANdF",
      "name": "",
      "number": ""
    },
    {
      "id": "r_8_vgjU_Gvlv8ccL9hnX",
      "name": "",
      "number": "3"
    },
    {
      "id": "u9c_4yihd8tmccMOIgZA4",
      "name": "seagul",
      "number": "23"
    },
    {
      "id": "XrDPyHyzSx4nNWPoORr3y",
      "name": "thrush",
      "number": "4"
    },
    {
      "id": "sMEpN9qsJH4Fhj71VP7aI",
      "name": "",
      "number": ""
    },
    {
      "id": "LCX1XB9oqePpe4-kxRCh9",
      "name": "blue tit",
      "number": "1"
    }
  ]
}